LICENSE
README.md
setup.cfg
setup.py
topsis_dilmanpreet_101903506/mmain.py
topsis_dilmanpreet_101903506.egg-info/PKG-INFO
topsis_dilmanpreet_101903506.egg-info/SOURCES.txt
topsis_dilmanpreet_101903506.egg-info/dependency_links.txt
topsis_dilmanpreet_101903506.egg-info/entry_points.txt
topsis_dilmanpreet_101903506.egg-info/requires.txt
topsis_dilmanpreet_101903506.egg-info/top_level.txt