Metadata-Version: 2.1
Name: topsis-dilmanpreet-101903506
Version: 1.2
Summary: It's a package that calcuates Topsis score and ranks accordingly
Home-page: https://github.com/dpsingh287/topsis-test-101
Author: Dilmanpreet Singh
Author-email: singh.dp.287@gmail.com
License: MIT
Download-URL: https://github.com/dpsingh287/topsis_dilmanpreet_101903506/archive/refs/tags/v10.tar.gz
Platform: UNKNOWN
Classifier: Programming Language :: Python :: 3
Classifier: License :: OSI Approved :: MIT License
Classifier: Operating System :: OS Independent
